locatieserver/__init__.py
locatieserver/client/__init__.py
locatieserver/client/config.py
locatieserver/client/free.py
locatieserver/client/lookup.py
locatieserver/client/suggest.py
locatieserver/client/utils.py
locatieserver/py.typed
locatieserver/schema/__init__.py
locatieserver/schema/base.py
locatieserver/schema/error.json
locatieserver/schema/error.py
locatieserver/schema/free.json
locatieserver/schema/free.py
locatieserver/schema/lookup.json
locatieserver/schema/lookup.py
locatieserver/schema/suggest.json
locatieserver/schema/suggest.py
locatieserver/schema/utils.py
locatieserver-0.6.0.dist-info/LICENSE
locatieserver-0.6.0.dist-info/METADATA
locatieserver-0.6.0.dist-info/WHEEL
locatieserver-0.6.0.dist-info/entry_points.txt
locatieserver-0.6.0.dist-info/RECORD
