Metadata-Version: 2.1
Name: locatieserver
Version: 0.6.0
Summary: Locatieserver
Home-page: https://github.com/foarsitter/locatieserver
License: MIT
Author: Jelmer Draaijer
Author-email: info@jelmert.nl
Requires-Python: >=3.8.1
Classifier: Development Status :: 4 - Beta
Classifier: License :: OSI Approved :: MIT License
Classifier: Programming Language :: Python :: 3
Classifier: Programming Language :: Python :: 3.9
Classifier: Programming Language :: Python :: 3.10
Classifier: Programming Language :: Python :: 3.11
Requires-Dist: httpx
Requires-Dist: pydantic (>=2.0.0,<3.0.0)
Project-URL: Changelog, https://github.com/foarsitter/locatieserver/releases
Project-URL: Documentation, https://locatieserver.readthedocs.io
Project-URL: Repository, https://github.com/foarsitter/locatieserver
